py2048/Board.py
py2048/Board_Test.py
py2048/Button.py
py2048/__init__.py
py2048/__main__.py
py2048/downloader.py
py2048/measures.py
py2048/move_window.py
py2048_coolin-0.3.1.dist-info/LICENSE
py2048_coolin-0.3.1.dist-info/METADATA
py2048_coolin-0.3.1.dist-info/WHEEL
py2048_coolin-0.3.1.dist-info/entry_points.txt
py2048_coolin-0.3.1.dist-info/top_level.txt
py2048_coolin-0.3.1.dist-info/RECORD
