Metadata-Version: 2.1
Name: py2048-coolin
Version: 0.3.1
Summary: 2048 game written with Pygame
Home-page: https://github.com/xXCoolinXx/2048
Author: Collin Francel
Author-email: collin.t.francel@gmail.com
License: UNKNOWN
Project-URL: Bug Tracker, https://github.com/xXCoolinXx/2048/issues
Platform: UNKNOWN
Classifier: Programming Language :: Python :: 3
Classifier: License :: OSI Approved :: GNU General Public License v3 or later (GPLv3+)
Classifier: Operating System :: OS Independent
Requires-Python: >=3.6
License-File: LICENSE
Requires-Dist: appdirs
Requires-Dist: jsonpickle
Requires-Dist: pygame
Requires-Dist: requests
Requires-Dist: results
